skosprovider_sqlalchemy/__init__.py
skosprovider_sqlalchemy/models.py
skosprovider_sqlalchemy/providers.py
skosprovider_sqlalchemy/utils.py
skosprovider_sqlalchemy/scripts/__init__.py
skosprovider_sqlalchemy/scripts/calc_visitation.py
skosprovider_sqlalchemy/scripts/init_skos_db.py
skosprovider_sqlalchemy-2.2.0.dist-info/METADATA
skosprovider_sqlalchemy-2.2.0.dist-info/WHEEL
skosprovider_sqlalchemy-2.2.0.dist-info/entry_points.txt
skosprovider_sqlalchemy-2.2.0.dist-info/licenses/LICENSE
skosprovider_sqlalchemy-2.2.0.dist-info/RECORD
