Metadata-Version: 2.4
Name: skosprovider_sqlalchemy
Version: 2.2.0
Summary: skosprovider_sqlalchemy
Project-URL: History, https://github.com/OnroerendErfgoed/skosprovider_sqlalchemy/blob/master/HISTORY.rst
Project-URL: Tracker, https://github.com/OnroerendErfgoed/skosprovider_sqlalchemy/issues
Project-URL: Source, https://github.com/OnroerendErfgoed/skosprovider_sqlalchemy
Project-URL: Documentation, https://skosprovider_sqlalchemy.readthedocs.io/en/latest/
Author-email: Flanders Heritage Agency <ict@onroerenderfgoed.be>
License-Expression: MIT
License-File: LICENSE
Keywords: rdf,skos,skosprovider,thesauri,vocabularies
Classifier: Development Status :: 5 - Production/Stable
Classifier: Framework :: Pyramid
Classifier: Programming Language :: Python
Classifier: Programming Language :: Python :: 3.10
Classifier: Programming Language :: Python :: 3.11
Classifier: Programming Language :: Python :: 3.12
Classifier: Programming Language :: Python :: 3.13
Classifier: Topic :: Internet :: WWW/HTTP
Classifier: Topic :: Internet :: WWW/HTTP :: WSGI :: Application
Requires-Python: <3.13.11,>=3.10
Requires-Dist: skosprovider>=1.2.0
Requires-Dist: sqlalchemy>=2.0.35
Provides-Extra: dev
Requires-Dist: coveralls>=4.0.1; extra == 'dev'
Requires-Dist: flake8>=7.1.1; extra == 'dev'
Requires-Dist: psycopg2-binary>=2.9.9; extra == 'dev'
Requires-Dist: pytest-cov>=5.0.0; extra == 'dev'
Requires-Dist: pytest>=8.3.3; extra == 'dev'
Requires-Dist: sphinx>=8.0.2; extra == 'dev'
Requires-Dist: uv>=0.4.11; extra == 'dev'
